README.rst
setup.py
lettoo_phone_quick_signup.egg-info/PKG-INFO
lettoo_phone_quick_signup.egg-info/SOURCES.txt
lettoo_phone_quick_signup.egg-info/dependency_links.txt
lettoo_phone_quick_signup.egg-info/not-zip-safe
lettoo_phone_quick_signup.egg-info/requires.txt
lettoo_phone_quick_signup.egg-info/top_level.txt
phone_quick_signup/__init__.py
phone_quick_signup/adapter.py
phone_quick_signup/admin.py
phone_quick_signup/app_settings.py
phone_quick_signup/forms.py
phone_quick_signup/managers.py
phone_quick_signup/models.py
phone_quick_signup/signals.py
phone_quick_signup/status.py
phone_quick_signup/urls.py
phone_quick_signup/utils.py
phone_quick_signup/views.py
phone_quick_signup/backends/__init__.py
phone_quick_signup/backends/base.py
phone_quick_signup/backends/console.py
phone_quick_signup/backends/yuntongxun.py
phone_quick_signup/locale/__init__.py
phone_quick_signup/locale/zh_Hans/__init__.py
phone_quick_signup/locale/zh_Hans/LC_MESSAGES/django.po
phone_quick_signup/migrations/0001_initial.py
phone_quick_signup/migrations/__init__.py