Metadata-Version: 1.1
Name: lettoo-phone-quick-signup
Version: 1.1.8
Summary: Django social authentication made simple.
Home-page: https://mingyugu@bitbucket.org/lettoo/lettoo_phone_quick_signup.git
Author: Mingyu Gu
Author-email: mingyugu0410@gmail.com
License: BSD
Keywords: django,openid,oauth,social auth,application
Platform: UNKNOWN
Classifier: Framework :: Django
Classifier: Development Status :: 4 - Beta
Classifier: Topic :: Internet
Classifier: License :: OSI Approved :: BSD License
Classifier: Intended Audience :: Developers
Classifier: Environment :: Web Environment
Classifier: Programming Language :: Python :: 2.5
Classifier: Programming Language :: Python :: 2.6
Classifier: Programming Language :: Python :: 2.7
